{"pax":{"mape":8.6,"months_history":135,"latest":"2026-03","seasonal12":[0.7589,0.7274,0.8833,0.9579,1.0723,1.1235,1.2383,1.2152,1.0951,1.1304,0.8982,0.9382],"holidays":["Republic of Latvia Proclamation Day","New Year's Day","Midsummer Day","Midsummer Eve","Constitutional Assembly Convocation Day; Labor Day"],"holidays_total":35,"gdpRegressor":false,"gdpForecast":false,"forecast":[{"date":"2026-04","y":2026,"m":3,"v":605092,"lo":578419,"hi":634453},{"date":"2026-05","y":2026,"m":4,"v":662672,"lo":635587,"hi":691152},{"date":"2026-06","y":2026,"m":5,"v":711808,"lo":686223,"hi":737788},{"date":"2026-07","y":2026,"m":6,"v":771579,"lo":744375,"hi":799861},{"date":"2026-08","y":2026,"m":7,"v":764128,"lo":735857,"hi":791127},{"date":"2026-09","y":2026,"m":8,"v":677765,"lo":651850,"hi":707649},{"date":"2026-10","y":2026,"m":9,"v":676786,"lo":646085,"hi":705652},{"date":"2026-11","y":2026,"m":10,"v":545567,"lo":515786,"hi":576093},{"date":"2026-12","y":2026,"m":11,"v":550609,"lo":518555,"hi":581967},{"date":"2027-01","y":2027,"m":0,"v":477445,"lo":448743,"hi":508473},{"date":"2027-02","y":2027,"m":1,"v":447221,"lo":413462,"hi":481231},{"date":"2027-03","y":2027,"m":2,"v":569027,"lo":534807,"hi":604447},{"date":"2027-04","y":2027,"m":3,"v":597233,"lo":559473,"hi":634993},{"date":"2027-05","y":2027,"m":4,"v":685842,"lo":646178,"hi":726856},{"date":"2027-06","y":2027,"m":5,"v":728299,"lo":683257,"hi":774827},{"date":"2027-07","y":2027,"m":6,"v":791460,"lo":743539,"hi":844033},{"date":"2027-08","y":2027,"m":7,"v":790360,"lo":735509,"hi":847956},{"date":"2027-09","y":2027,"m":8,"v":696693,"lo":648328,"hi":749826},{"date":"2027-10","y":2027,"m":9,"v":700431,"lo":647375,"hi":754501},{"date":"2027-11","y":2027,"m":10,"v":565653,"lo":514864,"hi":617758},{"date":"2027-12","y":2027,"m":11,"v":568981,"lo":519195,"hi":623413},{"date":"2028-01","y":2028,"m":0,"v":486280,"lo":438256,"hi":538016},{"date":"2028-02","y":2028,"m":1,"v":461844,"lo":412832,"hi":514990},{"date":"2028-03","y":2028,"m":2,"v":564361,"lo":508089,"hi":627378}]},"atm":{"mape":7.9,"months_history":135,"latest":"2026-03","seasonal12":[0.8355,0.7676,0.938,0.9853,1.099,1.0854,1.1256,1.1205,1.0827,1.0955,0.9273,0.9581],"holidays":["Republic of Latvia Proclamation Day","New Year's Day","Constitutional Assembly Convocation Day; Labor Day","Mother's Day","Restoration of Independence Day"],"holidays_total":35,"gdpRegressor":false,"gdpForecast":false,"forecast":[{"date":"2026-04","y":2026,"m":3,"v":4937,"lo":4759,"hi":5118},{"date":"2026-05","y":2026,"m":4,"v":5408,"lo":5248,"hi":5590},{"date":"2026-06","y":2026,"m":5,"v":5335,"lo":5152,"hi":5524},{"date":"2026-07","y":2026,"m":6,"v":5511,"lo":5329,"hi":5684},{"date":"2026-08","y":2026,"m":7,"v":5564,"lo":5379,"hi":5755},{"date":"2026-09","y":2026,"m":8,"v":5333,"lo":5110,"hi":5537},{"date":"2026-10","y":2026,"m":9,"v":5304,"lo":5098,"hi":5521},{"date":"2026-11","y":2026,"m":10,"v":4502,"lo":4280,"hi":4716},{"date":"2026-12","y":2026,"m":11,"v":4561,"lo":4327,"hi":4791},{"date":"2027-01","y":2027,"m":0,"v":4349,"lo":4120,"hi":4614},{"date":"2027-02","y":2027,"m":1,"v":3878,"lo":3627,"hi":4130},{"date":"2027-03","y":2027,"m":2,"v":4517,"lo":4203,"hi":4809},{"date":"2027-04","y":2027,"m":3,"v":5082,"lo":4720,"hi":5416},{"date":"2027-05","y":2027,"m":4,"v":5526,"lo":5116,"hi":5949},{"date":"2027-06","y":2027,"m":5,"v":5352,"lo":4905,"hi":5789},{"date":"2027-07","y":2027,"m":6,"v":5581,"lo":5104,"hi":6064},{"date":"2027-08","y":2027,"m":7,"v":5666,"lo":5142,"hi":6172},{"date":"2027-09","y":2027,"m":8,"v":5403,"lo":4810,"hi":5939},{"date":"2027-10","y":2027,"m":9,"v":5418,"lo":4793,"hi":6018},{"date":"2027-11","y":2027,"m":10,"v":4607,"lo":4044,"hi":5178},{"date":"2027-12","y":2027,"m":11,"v":4646,"lo":4060,"hi":5259},{"date":"2028-01","y":2028,"m":0,"v":4362,"lo":3741,"hi":4989},{"date":"2028-02","y":2028,"m":1,"v":3951,"lo":3353,"hi":4557},{"date":"2028-03","y":2028,"m":2,"v":4701,"lo":3976,"hi":5447}]},"cargo":{"mape":25.9,"months_history":135,"latest":"2026-03","seasonal12":[1.0041,0.9702,1.0762,0.877,0.9046,0.9091,0.9547,0.9295,1.0107,1.0298,1.0792,1.2297],"holidays":["Republic of Latvia Proclamation Day","New Year's Day","Easter Sunday","Midsummer Day","Midsummer Eve"],"holidays_total":35,"gdpRegressor":false,"gdpForecast":false,"forecast":[{"date":"2026-04","y":2026,"m":3,"v":1611,"lo":1387,"hi":1835},{"date":"2026-05","y":2026,"m":4,"v":1689,"lo":1478,"hi":1933},{"date":"2026-06","y":2026,"m":5,"v":1700,"lo":1493,"hi":1924},{"date":"2026-07","y":2026,"m":6,"v":1809,"lo":1568,"hi":2029},{"date":"2026-08","y":2026,"m":7,"v":1821,"lo":1588,"hi":2059},{"date":"2026-09","y":2026,"m":8,"v":1820,"lo":1581,"hi":2047},{"date":"2026-10","y":2026,"m":9,"v":1969,"lo":1732,"hi":2186},{"date":"2026-11","y":2026,"m":10,"v":2014,"lo":1784,"hi":2246},{"date":"2026-12","y":2026,"m":11,"v":2211,"lo":1988,"hi":2425},{"date":"2027-01","y":2027,"m":0,"v":1825,"lo":1587,"hi":2058},{"date":"2027-02","y":2027,"m":1,"v":1844,"lo":1596,"hi":2074},{"date":"2027-03","y":2027,"m":2,"v":1902,"lo":1662,"hi":2136},{"date":"2027-04","y":2027,"m":3,"v":1747,"lo":1506,"hi":1979},{"date":"2027-05","y":2027,"m":4,"v":1801,"lo":1566,"hi":2047},{"date":"2027-06","y":2027,"m":5,"v":1807,"lo":1589,"hi":2048},{"date":"2027-07","y":2027,"m":6,"v":1920,"lo":1684,"hi":2155},{"date":"2027-08","y":2027,"m":7,"v":1941,"lo":1714,"hi":2181},{"date":"2027-09","y":2027,"m":8,"v":1932,"lo":1678,"hi":2160},{"date":"2027-10","y":2027,"m":9,"v":2096,"lo":1846,"hi":2346},{"date":"2027-11","y":2027,"m":10,"v":2143,"lo":1892,"hi":2393},{"date":"2027-12","y":2027,"m":11,"v":2353,"lo":2104,"hi":2598},{"date":"2028-01","y":2028,"m":0,"v":1934,"lo":1699,"hi":2187},{"date":"2028-02","y":2028,"m":1,"v":1959,"lo":1717,"hi":2220},{"date":"2028-03","y":2028,"m":2,"v":2052,"lo":1789,"hi":2306}]}}
