{"pax":{"mape":6.2,"months_history":136,"latest":"2026-04","seasonal12":[0.7595,0.7247,0.8789,1.0541,1.0752,1.0982,1.1715,1.2109,1.162,1.13,0.8574,0.8595],"holidays":["Anti-Fascist Struggle Day","Assumption Day","Victory and Homeland Thanksgiving Day and Croatian Veterans Day","All Saints' Day","Christmas Day"],"holidays_total":16,"gdpRegressor":true,"gdpForecast":false,"forecast":[{"date":"2026-05","y":2026,"m":4,"v":466550,"lo":452674,"hi":479340},{"date":"2026-06","y":2026,"m":5,"v":487446,"lo":474133,"hi":500715},{"date":"2026-07","y":2026,"m":6,"v":538951,"lo":525431,"hi":552208},{"date":"2026-08","y":2026,"m":7,"v":550652,"lo":537408,"hi":563715},{"date":"2026-09","y":2026,"m":8,"v":524903,"lo":509874,"hi":538291},{"date":"2026-10","y":2026,"m":9,"v":507902,"lo":494591,"hi":521806},{"date":"2026-11","y":2026,"m":10,"v":395130,"lo":380772,"hi":409485},{"date":"2026-12","y":2026,"m":11,"v":383725,"lo":369138,"hi":397674},{"date":"2027-01","y":2027,"m":0,"v":346033,"lo":331520,"hi":359865},{"date":"2027-02","y":2027,"m":1,"v":331314,"lo":317134,"hi":345659},{"date":"2027-03","y":2027,"m":2,"v":439803,"lo":424634,"hi":453904},{"date":"2027-04","y":2027,"m":3,"v":437635,"lo":423141,"hi":453427},{"date":"2027-05","y":2027,"m":4,"v":520289,"lo":504966,"hi":537229},{"date":"2027-06","y":2027,"m":5,"v":545365,"lo":528638,"hi":561917},{"date":"2027-07","y":2027,"m":6,"v":600314,"lo":583807,"hi":616351},{"date":"2027-08","y":2027,"m":7,"v":612473,"lo":594962,"hi":630794},{"date":"2027-09","y":2027,"m":8,"v":583687,"lo":567363,"hi":600664},{"date":"2027-10","y":2027,"m":9,"v":566825,"lo":548031,"hi":585838},{"date":"2027-11","y":2027,"m":10,"v":446106,"lo":429438,"hi":463582},{"date":"2027-12","y":2027,"m":11,"v":430904,"lo":413099,"hi":448606},{"date":"2028-01","y":2028,"m":0,"v":391759,"lo":374893,"hi":409809},{"date":"2028-02","y":2028,"m":1,"v":374031,"lo":358428,"hi":393398},{"date":"2028-03","y":2028,"m":2,"v":447950,"lo":429959,"hi":467715},{"date":"2028-04","y":2028,"m":3,"v":537984,"lo":517583,"hi":558423}]},"atm":{"mape":8.0,"months_history":136,"latest":"2026-04","seasonal12":[0.8775,0.787,0.918,1.0418,1.0522,1.0466,1.1246,1.1386,1.0925,1.0939,0.9028,0.9104],"holidays":["Anti-Fascist Struggle Day","Epiphany","New Year's Day","Christmas Day","Saint Stephen's Day"],"holidays_total":16,"gdpRegressor":true,"gdpForecast":false,"forecast":[{"date":"2026-05","y":2026,"m":4,"v":4204,"lo":4056,"hi":4347},{"date":"2026-06","y":2026,"m":5,"v":4244,"lo":4097,"hi":4387},{"date":"2026-07","y":2026,"m":6,"v":4545,"lo":4403,"hi":4677},{"date":"2026-08","y":2026,"m":7,"v":4638,"lo":4483,"hi":4779},{"date":"2026-09","y":2026,"m":8,"v":4396,"lo":4267,"hi":4549},{"date":"2026-10","y":2026,"m":9,"v":4374,"lo":4227,"hi":4523},{"date":"2026-11","y":2026,"m":10,"v":3607,"lo":3464,"hi":3756},{"date":"2026-12","y":2026,"m":11,"v":3463,"lo":3322,"hi":3610},{"date":"2027-01","y":2027,"m":0,"v":3413,"lo":3272,"hi":3563},{"date":"2027-02","y":2027,"m":1,"v":3068,"lo":2929,"hi":3218},{"date":"2027-03","y":2027,"m":2,"v":3786,"lo":3627,"hi":3931},{"date":"2027-04","y":2027,"m":3,"v":3927,"lo":3776,"hi":4071},{"date":"2027-05","y":2027,"m":4,"v":4411,"lo":4275,"hi":4566},{"date":"2027-06","y":2027,"m":5,"v":4508,"lo":4368,"hi":4664},{"date":"2027-07","y":2027,"m":6,"v":4796,"lo":4644,"hi":4949},{"date":"2027-08","y":2027,"m":7,"v":4898,"lo":4750,"hi":5052},{"date":"2027-09","y":2027,"m":8,"v":4637,"lo":4482,"hi":4790},{"date":"2027-10","y":2027,"m":9,"v":4609,"lo":4465,"hi":4771},{"date":"2027-11","y":2027,"m":10,"v":3805,"lo":3648,"hi":3962},{"date":"2027-12","y":2027,"m":11,"v":3626,"lo":3477,"hi":3778},{"date":"2028-01","y":2028,"m":0,"v":3583,"lo":3426,"hi":3736},{"date":"2028-02","y":2028,"m":1,"v":3215,"lo":3062,"hi":3377},{"date":"2028-03","y":2028,"m":2,"v":3793,"lo":3637,"hi":3950},{"date":"2028-04","y":2028,"m":3,"v":4335,"lo":4176,"hi":4506}]},"cargo":{"mape":8.6,"months_history":136,"latest":"2026-04","seasonal12":[0.8663,0.8456,1.0656,0.9244,1.0606,1.083,1.1282,0.9335,1.134,1.0557,0.9065,1.0217],"holidays":["Easter Sunday","Easter Monday","Remembrance Day","Statehood Day","Corpus Christi"],"holidays_total":16,"gdpRegressor":true,"gdpForecast":false,"forecast":[{"date":"2026-05","y":2026,"m":4,"v":728,"lo":600,"hi":842},{"date":"2026-06","y":2026,"m":5,"v":765,"lo":639,"hi":884},{"date":"2026-07","y":2026,"m":6,"v":786,"lo":667,"hi":909},{"date":"2026-08","y":2026,"m":7,"v":722,"lo":600,"hi":839},{"date":"2026-09","y":2026,"m":8,"v":804,"lo":687,"hi":925},{"date":"2026-10","y":2026,"m":9,"v":734,"lo":620,"hi":854},{"date":"2026-11","y":2026,"m":10,"v":682,"lo":566,"hi":814},{"date":"2026-12","y":2026,"m":11,"v":747,"lo":622,"hi":869},{"date":"2027-01","y":2027,"m":0,"v":661,"lo":539,"hi":788},{"date":"2027-02","y":2027,"m":1,"v":657,"lo":533,"hi":783},{"date":"2027-03","y":2027,"m":2,"v":711,"lo":591,"hi":839},{"date":"2027-04","y":2027,"m":3,"v":687,"lo":554,"hi":799},{"date":"2027-05","y":2027,"m":4,"v":661,"lo":537,"hi":786},{"date":"2027-06","y":2027,"m":5,"v":755,"lo":633,"hi":876},{"date":"2027-07","y":2027,"m":6,"v":740,"lo":619,"hi":865},{"date":"2027-08","y":2027,"m":7,"v":684,"lo":559,"hi":809},{"date":"2027-09","y":2027,"m":8,"v":750,"lo":623,"hi":874},{"date":"2027-10","y":2027,"m":9,"v":691,"lo":564,"hi":810},{"date":"2027-11","y":2027,"m":10,"v":642,"lo":522,"hi":763},{"date":"2027-12","y":2027,"m":11,"v":698,"lo":577,"hi":821},{"date":"2028-01","y":2028,"m":0,"v":622,"lo":492,"hi":739},{"date":"2028-02","y":2028,"m":1,"v":616,"lo":494,"hi":751},{"date":"2028-03","y":2028,"m":2,"v":655,"lo":523,"hi":781},{"date":"2028-04","y":2028,"m":3,"v":643,"lo":518,"hi":768}]}}
